Metadata-Version: 2.1
Name: starknet-py-unbroken
Version: 0.24.5
Summary: A python SDK for Starknet
Home-page: https://github.com/software-mansion/starknet.py
License: MIT
Author: Tomasz Rejowski
Author-email: tomasz.rejowski@swmansion.com
Requires-Python: >=3.8,<3.13
Classifier: License :: OSI Approved :: MIT License
Classifier: Programming Language :: Python :: 3
Classifier: Programming Language :: Python :: 3.8
Classifier: Programming Language :: Python :: 3.9
Classifier: Programming Language :: Python :: 3.10
Classifier: Programming Language :: Python :: 3.11
Classifier: Programming Language :: Python :: 3.12
Provides-Extra: docs
Requires-Dist: aiohttp (>=3.8.4,<4.0.0)
Requires-Dist: asgiref (>=3.4.1,<4.0.0)
Requires-Dist: bip-utils (>=2.9.3,<3.0.0)
Requires-Dist: crypto-cpp-py (==1.4.4)
Requires-Dist: enum-tools[sphinx] (==0.12.0) ; extra == "docs"
Requires-Dist: eth-keyfile (>=0.8.1,<0.9.0)
Requires-Dist: furo (>=2024.5.6,<2025.0.0) ; extra == "docs"
Requires-Dist: lark (>=1.1.5,<2.0.0)
Requires-Dist: ledgerwallet (>=0.5.0,<0.6.0)
Requires-Dist: marshmallow (>=3.15.0,<4.0.0)
Requires-Dist: marshmallow-dataclass (<8.8.0)
Requires-Dist: marshmallow-oneofschema (==3.1.1)
Requires-Dist: poseidon-py (==0.1.5)
Requires-Dist: pycryptodome (>=3.17,<4.0)
Requires-Dist: sphinx (>=4.3.1,<8.0.0) ; extra == "docs"
Requires-Dist: typing-extensions (>=4.3.0,<5.0.0)
Project-URL: Documentation, https://starknetpy.rtfd.io/
Project-URL: Repository, https://github.com/software-mansion/starknet.py
